mailship/__init__.py
mailship/auth.py
mailship/email_generator.py
mailship/email_listener.py
mailship/email_parser.py
mailship/operations.py
mailship/setup_auth.py
mailship-1.0.3.dist-info/LICENSE
mailship-1.0.3.dist-info/METADATA
mailship-1.0.3.dist-info/WHEEL
mailship-1.0.3.dist-info/entry_points.txt
mailship-1.0.3.dist-info/top_level.txt
mailship-1.0.3.dist-info/RECORD
