Metadata-Version: 2.1
Name: mailship
Version: 1.0.3
Summary: Mail Ship: A powerful Python library for email automation and testing. It offers Gmail integration, real-time inbox monitoring, content extraction, and seamless Selenium integration. Perfect for developers navigating complex email-based workflows and testing scenarios.
Home-page: https://github.com/BlazinArtemis/mail_ship/
Author: Oluwaseyi Ajadi
Author-email: oluwaseyinexus137@gmail.com
Classifier: Development Status :: 3 - Alpha
Classifier: Intended Audience :: Developers
Classifier: Operating System :: OS Independent
Classifier: Programming Language :: Python :: 3
Classifier: Programming Language :: Python :: 3.7
Classifier: Programming Language :: Python :: 3.8
Classifier: Programming Language :: Python :: 3.9
Requires-Python: >=3.7
License-File: LICENSE
Requires-Dist: google-auth-oauthlib
Requires-Dist: google-auth-httplib2
Requires-Dist: google-api-python-client
Requires-Dist: beautifulsoup4
Requires-Dist: google-auth
Requires-Dist: cryptography
Requires-Dist: pyvirtualdisplay>=3.0
Requires-Dist: chromedriver-autoinstaller>=0.5
Requires-Dist: selenium>=4.0.0
